wasr_client/__init__.py
wasr_client/client.py
wasr_client/grpc.py
wasr_client-0.1.0.dist-info/WHEEL
wasr_client-0.1.0.dist-info/entry_points.txt
wasr_client-0.1.0.dist-info/METADATA
wasr_client-0.1.0.dist-info/RECORD
