Metadata-Version: 2.3
Name: wasr-client
Version: 0.1.0
Summary: Add your description here
Requires-Dist: grpc-interceptor>=0.15.4
Requires-Dist: grpcio>=1.76.0
Requires-Dist: seldon-core>=1.18.2
Requires-Python: >=3.10
